plone.app.iterate-6.3.2-py3.12-nspkg.pth
plone/app/iterate/__init__.py
plone/app/iterate/archiver.py
plone/app/iterate/base.py
plone/app/iterate/configure.zcml
plone/app/iterate/containers.py
plone/app/iterate/event.py
plone/app/iterate/indexer.py
plone/app/iterate/interfaces.py
plone/app/iterate/lock.py
plone/app/iterate/permissions.py
plone/app/iterate/setuphandlers.py
plone/app/iterate/testing.py
plone/app/iterate/util.py
plone/app/iterate/browser/__init__.py
plone/app/iterate/browser/cancel.png
plone/app/iterate/browser/cancel.pt
plone/app/iterate/browser/cancel.py
plone/app/iterate/browser/checkin.png
plone/app/iterate/browser/checkin.pt
plone/app/iterate/browser/checkin.py
plone/app/iterate/browser/checkout.png
plone/app/iterate/browser/checkout.pt
plone/app/iterate/browser/checkout.py
plone/app/iterate/browser/configure.zcml
plone/app/iterate/browser/control.py
plone/app/iterate/browser/diff.pt
plone/app/iterate/browser/diff.py
plone/app/iterate/browser/info.py
plone/app/iterate/browser/info_baseline.pt
plone/app/iterate/browser/info_checkout.pt
plone/app/iterate/dexterity/__init__.py
plone/app/iterate/dexterity/configure.zcml
plone/app/iterate/dexterity/copier.py
plone/app/iterate/dexterity/interfaces.py
plone/app/iterate/dexterity/policy.py
plone/app/iterate/dexterity/relation.py
plone/app/iterate/dexterity/utils.py
plone/app/iterate/profiles/default/actions.xml
plone/app/iterate/profiles/default/catalog.xml
plone/app/iterate/profiles/default/metadata.xml
plone/app/iterate/profiles/default/registry.xml
plone/app/iterate/profiles/default/rolemap.xml
plone/app/iterate/profiles/to1000/actions.xml
plone/app/iterate/profiles/uninstall/actions.xml
plone/app/iterate/profiles/uninstall/metadata.xml
plone/app/iterate/profiles/uninstall/registry.xml
plone/app/iterate/subscribers/__init__.py
plone/app/iterate/subscribers/configure.zcml
plone/app/iterate/subscribers/locking.py
plone/app/iterate/subscribers/marker.py
plone/app/iterate/subscribers/metadata.py
plone_app_iterate-6.3.2.dist-info/METADATA
plone_app_iterate-6.3.2.dist-info/WHEEL
plone_app_iterate-6.3.2.dist-info/entry_points.txt
plone_app_iterate-6.3.2.dist-info/namespace_packages.txt
plone_app_iterate-6.3.2.dist-info/top_level.txt
plone_app_iterate-6.3.2.dist-info/RECORD
