Metadata-Version: 2.4
Name: plone.app.iterate
Version: 6.3.2
Summary: check-out/check-in staging for Plone
Home-page: https://pypi.org/project/plone.app.iterate
Author: Plone Foundation
Author-email: plone-developers@lists.sourceforge.net
License: GPL version 2
Keywords: check-out check-in staging
Classifier: Development Status :: 5 - Production/Stable
Classifier: Environment :: Web Environment
Classifier: Framework :: Plone
Classifier: Framework :: Plone :: 6.0
Classifier: Framework :: Plone :: Core
Classifier: Framework :: Zope :: 5
Classifier: License :: OSI Approved :: GNU General Public License v2 (GPLv2)
Classifier: Operating System :: OS Independent
Classifier: Programming Language :: Python
Classifier: Programming Language :: Python :: 3.8
Classifier: Programming Language :: Python :: 3.9
Classifier: Programming Language :: Python :: 3.10
Classifier: Programming Language :: Python :: 3.11
Requires-Python: >=3.8
Requires-Dist: Acquisition
Requires-Dist: DateTime
Requires-Dist: plone.app.relationfield
Requires-Dist: plone.indexer
Requires-Dist: plone.locking
Requires-Dist: plone.memoize
Requires-Dist: Products.CMFEditions
Requires-Dist: Products.CMFPlacefulWorkflow
Requires-Dist: Products.DCWorkflow
Requires-Dist: Products.GenericSetup>=1.8.2
Requires-Dist: Products.statusmessages
Requires-Dist: setuptools
Requires-Dist: Zope
Requires-Dist: plone.app.layout
Requires-Dist: plone.base
Requires-Dist: plone.dexterity
Requires-Dist: plone.registry
Requires-Dist: z3c.relationfield
Requires-Dist: zc.relation
Requires-Dist: zope.intid
Provides-Extra: test
Requires-Dist: plone.app.testing; extra == "test"
Requires-Dist: plone.app.contenttypes[test]; extra == "test"
Requires-Dist: plone.testing; extra == "test"
Dynamic: author
Dynamic: author-email
Dynamic: classifier
Dynamic: description
Dynamic: description-content-type
Dynamic: home-page
Dynamic: keywords
Dynamic: license
Dynamic: provides-extra
Dynamic: requires-dist
Dynamic: requires-python
Dynamic: summary
